[
  {
    "id": 3060,
    "title": "Commercial Ground-Up Construction",
    "url": "/for-ground-up-construction",
    "classes": []
  },
  {
    "id": 3136,
    "title": "Tenant Improvements",
    "url": "/for-tenant-improvement",
    "classes": []
  },
  {
    "id": 3635,
    "title": "Mixed-Use Buildings",
    "url": "https://prostructengineering.com/commercial-structural-engineers/for-mixed-use-buildings/",
    "classes": []
  },
  {
    "id": 3636,
    "title": "Apartment Buildings/ Townhouses",
    "url": "https://prostructengineering.com/commercial-structural-engineers/for-apartment-buildings/",
    "classes": []
  },
  {
    "id": 3637,
    "title": "Equipment Anchorage",
    "url": "https://prostructengineering.com/commercial-structural-engineers/for-equipment-anchorage/",
    "classes": []
  }
]